<?xml version='1.0' encoding="utf-8" standalone='yes'?>
<page_info>
	<language_info>		
		<System_Description_Control>
			<text>Description Contrôle du système</text>
		</System_Description_Control>
		<Description_Table>
			<text>Tableau de description</text>
		</Description_Table>
	</language_info>	
	<help_info>	
		<help_step>
			<name>tour_1</name>
			<bgcolor>#36454F</bgcolor>
			<color>white</color>
			<position>TR</position>
			<text>Sélectionnez le menu déroulant pour filtrer la liste Description.</text>
			<time>5000</time>
		</help_step>	
		<help_step>
			<name>tour_2</name>
			<bgcolor>#36454F</bgcolor>
			<color>white</color>
			<position>TR</position>
			<text>Entrez les champs de formulaire de droite pour ajouter un nouvel enregistrement.</text>
			<time>5000</time>
		</help_step>		
	</help_info>
</page_info>